{
    "$schema": "http://json-schema.org/draft-07/schema",
    "$id": "http://example.com/example.json",
    "type": "object",
    "title": "Contatti",
    "description": "The root schema comprises the entire JSON document.",
    "default": {},
    "examples": [
        {
            "instagram": "https://www.instagram.com/indiegekko/",
            "facebook": "https://www.facebook.com/IndieGekko-100314151912574",
            "email": "info@indiegekko.it",
            "telefono": "3401474729"
        }
    ],
    "required": [
        "instagram",
        "facebook",
        "email",
        "telefono"
    ],
    "properties": {
        "instagram": {
            "$id": "#/properties/instagram",
            "default": "",
            "description": "An explanation about the purpose of this instance.",
            "examples": [
                "https://www.instagram.com/indiegekko/"
            ],
            "title": "Instagram Link",
            "type": "string"
        },
        "facebook": {
            "$id": "#/properties/facebook",
            "default": "",
            "description": "An explanation about the purpose of this instance.",
            "examples": [
                "https://www.facebook.com/IndieGekko-100314151912574"
            ],
            "title": "Facebook Link",
            "type": "string"
        },
        "email": {
            "$id": "#/properties/email",
            "default": "",
            "description": "An explanation about the purpose of this instance.",
            "examples": [
                "info@indiegekko.it"
            ],
            "title": "E-mail",
            "type": "string"
        },
        "telefono": {
            "$id": "#/properties/telefono",
            "default": "",
            "description": "An explanation about the purpose of this instance.",
            "examples": [
                "3401474729"
            ],
            "title": "Telefono",
            "type": "string"
        }
    },
    "additionalProperties": true
}